README.rst
setup.py
examplescripts/pycorn-bin.py
pycorn/__init__.py
pycorn/pycorn.py
pycorn.egg-info/PKG-INFO
pycorn.egg-info/SOURCES.txt
pycorn.egg-info/dependency_links.txt
pycorn.egg-info/top_level.txt