Metadata-Version: 1.0
Name: pycorn
Version: 0.13
Summary: A script to extract data from UNICORN result (res) files
Home-page: https://github.com/pyahmed/PyCORN
Author: Yasar L. Ahmed
Author-email: UNKNOWN
License: GNU General Public License v2 (GPLv2)
Platform: UNKNOWN
